{"otherData": {},"traceEvents":[{"cat":"function","dur":60743,"name":"glfwInit","ph":"X","pid":0,"tid":3062903677,"ts":1021045987626},{"cat":"function","dur":214016,"name":"glfwCreateWindow","ph":"X","pid":0,"tid":3062903677,"ts":1021046048493},{"cat":"function","dur":6626,"name":"void __cdecl Hazel::OpenGLContext::Init(void)","ph":"X","pid":0,"tid":3062903677,"ts":1021046262597},{"cat":"function","dur":33,"name":"void __cdecl Hazel::WindowsWindow::SetVSync(bool)","ph":"X","pid":0,"tid":3062903677,"ts":1021046269282},{"cat":"function","dur":282508,"name":"__cdecl Hazel::WindowsWindow::WindowsWindow(const struct Hazel::WindowProps &)","ph":"X","pid":0,"tid":3062903677,"ts":1021045986828},{"cat":"function","dur":9,"name":"void __cdecl Hazel::WindowsWindow::SetVSync(bool)","ph":"X","pid":0,"tid":3062903677,"ts":1021046269363},{"cat":"function","dur":5,"name":"void __cdecl Hazel::OpenGLRendererAPI::Init(void)","ph":"X","pid":0,"tid":3062903677,"ts":1021046269389},{"cat":"function","dur":20,"name":"__cdecl Hazel::OpenGLVertexArray::OpenGLVertexArray(void)","ph":"X","pid":0,"tid":3062903677,"ts":1021046269416},{"cat":"function","dur":13,"name":"__cdecl Hazel::OpenGLVertexBuffer::OpenGLVertexBuffer(unsigned int)","ph":"X","pid":0,"tid":3062903677,"ts":1021046269463},{"cat":"function","dur":0,"name":"void __cdecl Hazel::OpenGLVertexBuffer::Bind(void) const","ph":"X","pid":0,"tid":3062903677,"ts":1021046269541},{"cat":"function","dur":57,"name":"void __cdecl Hazel::OpenGLVertexArray::AddVertexBuffer(const class std::shared_ptr<class Hazel::VertexBuffer> &)","ph":"X","pid":0,"tid":3062903677,"ts":1021046269508},{"cat":"function","dur":95,"name":"__cdecl Hazel::OpenGLIndexBuffer::OpenGLIndexBuffer(unsigned int *,unsigned int)","ph":"X","pid":0,"tid":3062903677,"ts":1021046270272},{"cat":"function","dur":0,"name":"void __cdecl Hazel::OpenGLIndexBuffer::Bind(void) const","ph":"X","pid":0,"tid":3062903677,"ts":1021046270415},{"cat":"function","dur":23,"name":"void __cdecl Hazel::OpenGLVertexArray::SetIndexBuffer(const class std::shared_ptr<class Hazel::IndexBuffer> &)","ph":"X","pid":0,"tid":3062903677,"ts":1021046270413},{"cat":"function","dur":480,"name":"__cdecl Hazel::OpenGLTexture2D::OpenGLTexture2D(unsigned int,unsigned int)","ph":"X","pid":0,"tid":3062903677,"ts":1021046270467},{"cat":"function","dur":9,"name":"void __cdecl Hazel::OpenGLTexture2D::SetData(void *,unsigned int)","ph":"X","pid":0,"tid":3062903677,"ts":1021046271012},{"cat":"function","dur":142,"name":"class std::basic_string<char,struct std::char_traits<char>,class std::allocator<char> > __cdecl Hazel::OpenGLShader::ReadFile(const class std::basic_string<char,struct std::char_traits<char>,class std::allocator<char> > &)","ph":"X","pid":0,"tid":3062903677,"ts":1021046271053},{"cat":"function","dur":38,"name":"class std::unordered_map<unsigned int,class std::basic_string<char,struct std::char_traits<char>,class std::allocator<char> >,struct std::hash<unsigned int>,struct std::equal_to<unsigned int>,class std::allocator<struct std::pair<unsigned int const ,class std::basic_string<char,struct std::char_traits<char>,class std::allocator<char> > > > > __cdecl Hazel::OpenGLShader::PreProcess(const class std::basic_string<char,struct std::char_traits<char>,class std::allocator<char> > &)","ph":"X","pid":0,"tid":3062903677,"ts":1021046271226},{"cat":"function","dur":640,"name":"void __cdecl Hazel::OpenGLShader::Compile(const class std::unordered_map<unsigned int,class std::basic_string<char,struct std::char_traits<char>,class std::allocator<char> >,struct std::hash<unsigned int>,struct std::equal_to<unsigned int>,class std::allocator<struct std::pair<unsigned int const ,class std::basic_string<char,struct std::char_traits<char>,class std::allocator<char> > > > > &)","ph":"X","pid":0,"tid":3062903677,"ts":1021046271288},{"cat":"function","dur":990,"name":"__cdecl Hazel::OpenGLShader::OpenGLShader(const class std::basic_string<char,struct std::char_traits<char>,class std::allocator<char> > &)","ph":"X","pid":0,"tid":3062903677,"ts":1021046271051},{"cat":"function","dur":2,"name":"void __cdecl Hazel::OpenGLShader::Bind(void) const","ph":"X","pid":0,"tid":3062903677,"ts":1021046272071},{"cat":"function","dur":35,"name":"void __cdecl Hazel::OpenGLShader::SetIntArray(const class std::basic_string<char,struct std::char_traits<char>,class std::allocator<char> > &,int *,unsigned int)","ph":"X","pid":0,"tid":3062903677,"ts":1021046272131},{"cat":"function","dur":2787,"name":"void __cdecl Hazel::Renderer2D::Init(void)","ph":"X","pid":0,"tid":3062903677,"ts":1021046269408},{"cat":"function","dur":2823,"name":"void __cdecl Hazel::Renderer::init(void)","ph":"X","pid":0,"tid":3062903677,"ts":1021046269387},{"cat":"function","dur":1225,"name":"void __cdecl Hazel::ImGuiLayer::OnAttach(void)","ph":"X","pid":0,"tid":3062903677,"ts":1021046272234},{"cat":"function","dur":1278,"name":"void __cdecl Hazel::Application::PushOverlay(class Hazel::Layer *)","ph":"X","pid":0,"tid":3062903677,"ts":1021046272231},{"cat":"function","dur":286705,"name":"__cdecl Hazel::Application::Application(const class std::basic_string<char,struct std::char_traits<char>,class std::allocator<char> > &)","ph":"X","pid":0,"tid":3062903677,"ts":1021045986819},{"cat":"function","dur":2,"name":"__cdecl Hazel::OrthographicCamera::OrthographicCamera(float,float,float,float)","ph":"X","pid":0,"tid":3062903677,"ts":1021046273543},{"cat":"function","dur":5839,"name":"stbi_load - OpenGLTexture2D::OpenGLTexture2D(const std::string&)","ph":"X","pid":0,"tid":3062903677,"ts":1021046273571},{"cat":"function","dur":6880,"name":"__cdecl Hazel::OpenGLTexture2D::OpenGLTexture2D(const class std::basic_string<char,struct std::char_traits<char>,class std::allocator<char> > &)","ph":"X","pid":0,"tid":3062903677,"ts":1021046273571},{"cat":"function","dur":8607,"name":"stbi_load - OpenGLTexture2D::OpenGLTexture2D(const std::string&)","ph":"X","pid":0,"tid":3062903677,"ts":1021046280528},{"cat":"function","dur":9290,"name":"__cdecl Hazel::OpenGLTexture2D::OpenGLTexture2D(const class std::basic_string<char,struct std::char_traits<char>,class std::allocator<char> > &)","ph":"X","pid":0,"tid":3062903677,"ts":1021046280527},{"cat":"function","dur":11450,"name":"stbi_load - OpenGLTexture2D::OpenGLTexture2D(const std::string&)","ph":"X","pid":0,"tid":3062903677,"ts":1021046289855},{"cat":"function","dur":13312,"name":"__cdecl Hazel::OpenGLTexture2D::OpenGLTexture2D(const class std::basic_string<char,struct std::char_traits<char>,class std::allocator<char> > &)","ph":"X","pid":0,"tid":3062903677,"ts":1021046289855},{"cat":"function","dur":31147,"name":"void __cdecl Hazel::EditorLayer::OnAttach(void)","ph":"X","pid":0,"tid":3062903677,"ts":1021046273568},{"cat":"function","dur":31205,"name":"void __cdecl Hazel::Application::PushLayer(class Hazel::Layer *)","ph":"X","pid":0,"tid":3062903677,"ts":1021046273560}]}